[
null,
{"id":1,"autoRemovalTiming":0,"chanceByDamage":100,"traits":[],"iconIndex":1,"maxTurns":1,"message1":"","message2":"","message3":"","message4":"","minTurns":1,"motion":0,"name":"Knockout","note":"","overlay":0,"priority":50,"removeAtBattleEnd":false,"removeByDamage":false,"removeByRestriction":false,"removeByWalking":false,"restriction":4,"stepsToRemove":100},
{"id":2,"autoRemovalTiming":2,"chanceByDamage":100,"description":"","iconIndex":531,"maxTurns":1,"message1":"","message2":"","message3":"","message4":"","minTurns":1,"motion":0,"name":"Guard","note":"","overlay":0,"priority":0,"removeAtBattleEnd":true,"removeByDamage":false,"removeByRestriction":true,"removeByWalking":false,"restriction":0,"stepsToRemove":100,"traits":[{"code":62,"dataId":1,"value":0}]},
{"id":3,"autoRemovalTiming":0,"chanceByDamage":100,"description":"","iconIndex":0,"maxTurns":1,"message1":"","message2":"","message3":"","message4":"","minTurns":1,"motion":0,"name":"Immortal","note":"","overlay":0,"priority":0,"removeAtBattleEnd":true,"removeByDamage":false,"removeByRestriction":false,"removeByWalking":false,"restriction":0,"stepsToRemove":100,"traits":[{"code":14,"dataId":1,"value":0}]},
{"id":4,"autoRemovalTiming":0,"chanceByDamage":100,"traits":[{"code":14,"dataId":1,"value":0},{"code":32,"dataId":14,"value":0.2}],"iconIndex":0,"maxTurns":1,"message1":"","message2":"","message3":"","message4":" is too hurt and backs out.","minTurns":1,"motion":0,"name":"Energiser","note":"<Passive Condition: MP Above 0%>\n   <Custom Barrier Regen 2 Turns>\n     user.gainMp(-user.mdf);\n     user.gainMp(-user.mat);\n     user.gainMp(user.hp-user.mhp);\n     user.gainHp(Math.floor((user.mhp-user.hp)/5));\n    value += user.mdf*12;\n   </Custom Barrier Regen 2 Turns>\n   <Custom Barrier Points 2 Turns>\n    value += user.mdf*12;\n   </Custom Barrier Points 2 Turns>\n\n<Custom Respond Effect>\n// Check to see if the party is in battle, has the Second Chance flag, and if the target is dead with 0 HP.\nif ($gameParty.inBattle() && target.hp <= 0) {\n  // Set the target's HP to 1.\n  target.setHp(1);\n}\n</Custom Respond Effect>","overlay":0,"priority":50,"removeAtBattleEnd":false,"removeByDamage":false,"removeByRestriction":false,"removeByWalking":false,"restriction":0,"stepsToRemove":100},
{"id":5,"autoRemovalTiming":0,"chanceByDamage":100,"traits":[],"iconIndex":0,"maxTurns":1,"message1":"","message2":"","message3":"","message4":"","minTurns":1,"motion":0,"name":"Engaged","note":"<Ally Aura: 6>  \n<Physical Taunt>\n  <Magical Taunt>\n  <Certain Taunt>","overlay":0,"priority":50,"removeAtBattleEnd":false,"removeByDamage":false,"removeByRestriction":false,"removeByWalking":false,"restriction":0,"stepsToRemove":100},
{"id":6,"autoRemovalTiming":0,"chanceByDamage":100,"traits":[],"iconIndex":0,"maxTurns":1,"message1":"","message2":"","message3":"","message4":"","minTurns":1,"motion":0,"name":"Engaged","note":"  <Custom Aura Condition>\n   if ($gameTroop.aliveMembers().length > 2) {\n     condition = true;\n   } else {\n     condition = false;\n   }\n  </Custom Aura Condition>","overlay":0,"priority":50,"removeAtBattleEnd":false,"removeByDamage":false,"removeByRestriction":false,"removeByWalking":false,"restriction":0,"stepsToRemove":100},
{"id":7,"autoRemovalTiming":1,"chanceByDamage":100,"traits":[{"code":21,"dataId":6,"value":1.5}],"iconIndex":5,"maxTurns":1,"message1":"","message2":"","message3":"","message4":"","minTurns":1,"motion":0,"name":"Rampaging","note":"<Reapply Ignore Turns>","overlay":0,"priority":50,"removeAtBattleEnd":true,"removeByDamage":false,"removeByRestriction":true,"removeByWalking":false,"restriction":0,"stepsToRemove":100},
{"id":8,"autoRemovalTiming":2,"chanceByDamage":100,"traits":[{"code":11,"dataId":1,"value":1.3}],"iconIndex":369,"maxTurns":3,"message1":"","message2":"","message3":"","message4":"","minTurns":3,"motion":0,"name":"Vector crossed","note":"","overlay":0,"priority":50,"removeAtBattleEnd":true,"removeByDamage":false,"removeByRestriction":false,"removeByWalking":false,"restriction":0,"stepsToRemove":100},
{"id":9,"autoRemovalTiming":0,"chanceByDamage":70,"traits":[],"iconIndex":468,"maxTurns":1,"message1":"","message2":"","message3":"","message4":"","minTurns":1,"motion":0,"name":"Horneted","note":"<DoT Formula:( a.mat * (100/a.agi) ) * 100/b.agi>","overlay":0,"priority":50,"removeAtBattleEnd":false,"removeByDamage":true,"removeByRestriction":false,"removeByWalking":false,"restriction":0,"stepsToRemove":100},
{"id":10,"autoRemovalTiming":2,"chanceByDamage":100,"traits":[{"code":11,"dataId":1,"value":10}],"iconIndex":566,"maxTurns":1,"message1":"","message2":"","message3":"","message4":"","minTurns":1,"motion":0,"name":"Widow Anchor","note":"","overlay":0,"priority":50,"removeAtBattleEnd":true,"removeByDamage":true,"removeByRestriction":false,"removeByWalking":false,"restriction":4,"stepsToRemove":100},
{"id":11,"autoRemovalTiming":2,"chanceByDamage":100,"traits":[{"code":11,"dataId":1,"value":10}],"iconIndex":574,"maxTurns":1,"message1":"","message2":"","message3":"","message4":"","minTurns":1,"motion":0,"name":"Smart Anchor","note":"<Custom Remove Effect>\nuser.addState(10);\n</Custom Remove Effect>\n","overlay":0,"priority":50,"removeAtBattleEnd":true,"removeByDamage":true,"removeByRestriction":false,"removeByWalking":false,"restriction":4,"stepsToRemove":100},
{"id":12,"autoRemovalTiming":0,"chanceByDamage":100,"traits":[{"code":44,"dataId":2,"value":1},{"code":44,"dataId":4,"value":1},{"code":44,"dataId":7,"value":1},{"code":44,"dataId":8,"value":1},{"code":44,"dataId":9,"value":1},{"code":44,"dataId":10,"value":1},{"code":44,"dataId":12,"value":1},{"code":44,"dataId":13,"value":1},{"code":44,"dataId":14,"value":1},{"code":44,"dataId":15,"value":1},{"code":44,"dataId":16,"value":1},{"code":44,"dataId":17,"value":1},{"code":44,"dataId":18,"value":1},{"code":44,"dataId":19,"value":1},{"code":44,"dataId":20,"value":1},{"code":44,"dataId":21,"value":1},{"code":44,"dataId":22,"value":1},{"code":44,"dataId":24,"value":1},{"code":44,"dataId":23,"value":1},{"code":44,"dataId":25,"value":1},{"code":44,"dataId":26,"value":1},{"code":44,"dataId":27,"value":1},{"code":44,"dataId":28,"value":1},{"code":44,"dataId":29,"value":1},{"code":44,"dataId":30,"value":1}],"iconIndex":0,"maxTurns":1,"message1":"","message2":"","message3":"","message4":"","minTurns":1,"motion":0,"name":"test restriction 1","note":"","overlay":0,"priority":50,"removeAtBattleEnd":false,"removeByDamage":false,"removeByRestriction":false,"removeByWalking":false,"restriction":0,"stepsToRemove":100},
{"id":13,"autoRemovalTiming":0,"chanceByDamage":100,"traits":[{"code":44,"dataId":2,"value":1},{"code":44,"dataId":4,"value":1},{"code":44,"dataId":7,"value":1},{"code":44,"dataId":8,"value":1},{"code":44,"dataId":9,"value":1},{"code":44,"dataId":10,"value":1},{"code":44,"dataId":11,"value":1},{"code":44,"dataId":13,"value":1},{"code":44,"dataId":14,"value":1},{"code":44,"dataId":15,"value":1},{"code":44,"dataId":16,"value":1},{"code":44,"dataId":17,"value":1},{"code":44,"dataId":18,"value":1},{"code":44,"dataId":19,"value":1},{"code":44,"dataId":20,"value":1},{"code":44,"dataId":21,"value":1},{"code":44,"dataId":22,"value":1},{"code":44,"dataId":24,"value":1},{"code":44,"dataId":23,"value":1},{"code":44,"dataId":25,"value":1},{"code":44,"dataId":26,"value":1},{"code":44,"dataId":27,"value":1},{"code":44,"dataId":28,"value":1},{"code":44,"dataId":29,"value":1},{"code":44,"dataId":30,"value":1}],"iconIndex":0,"maxTurns":1,"message1":"","message2":"","message3":"","message4":"","minTurns":1,"motion":0,"name":"test restriction 2","note":"","overlay":0,"priority":50,"removeAtBattleEnd":false,"removeByDamage":false,"removeByRestriction":false,"removeByWalking":false,"restriction":0,"stepsToRemove":100},
{"id":14,"autoRemovalTiming":2,"chanceByDamage":100,"traits":[{"code":22,"dataId":0,"value":5}],"iconIndex":5,"maxTurns":2,"message1":" is angry","message2":" has noticed you","message3":"","message4":"","minTurns":2,"motion":0,"name":"Angered","note":"","overlay":0,"priority":50,"removeAtBattleEnd":false,"removeByDamage":false,"removeByRestriction":false,"removeByWalking":false,"restriction":0,"stepsToRemove":100},
{"id":15,"autoRemovalTiming":0,"chanceByDamage":100,"traits":[{"code":44,"dataId":7,"value":1},{"code":44,"dataId":8,"value":1},{"code":44,"dataId":9,"value":1},{"code":44,"dataId":10,"value":1},{"code":44,"dataId":11,"value":1},{"code":44,"dataId":12,"value":1},{"code":44,"dataId":13,"value":1},{"code":44,"dataId":14,"value":1},{"code":44,"dataId":15,"value":1},{"code":44,"dataId":16,"value":1},{"code":44,"dataId":17,"value":1},{"code":44,"dataId":18,"value":1},{"code":44,"dataId":19,"value":1},{"code":44,"dataId":20,"value":1},{"code":44,"dataId":21,"value":1},{"code":44,"dataId":22,"value":1},{"code":44,"dataId":24,"value":1},{"code":44,"dataId":23,"value":1},{"code":44,"dataId":25,"value":1},{"code":44,"dataId":26,"value":1},{"code":44,"dataId":27,"value":1},{"code":44,"dataId":28,"value":1},{"code":44,"dataId":29,"value":1},{"code":44,"dataId":30,"value":1}],"iconIndex":0,"maxTurns":1,"message1":"","message2":"","message3":"","message4":"","minTurns":1,"motion":0,"name":"test restriction 3","note":"","overlay":0,"priority":50,"removeAtBattleEnd":false,"removeByDamage":false,"removeByRestriction":false,"removeByWalking":false,"restriction":0,"stepsToRemove":100},
{"id":16,"autoRemovalTiming":0,"chanceByDamage":100,"traits":[{"code":23,"dataId":0,"value":0},{"code":11,"dataId":1,"value":0},{"code":11,"dataId":2,"value":0},{"code":11,"dataId":3,"value":0},{"code":11,"dataId":4,"value":0},{"code":11,"dataId":5,"value":0},{"code":11,"dataId":6,"value":0},{"code":11,"dataId":7,"value":0},{"code":11,"dataId":8,"value":0},{"code":11,"dataId":9,"value":0},{"code":11,"dataId":10,"value":0},{"code":22,"dataId":1,"value":10}],"iconIndex":82,"maxTurns":1,"message1":"","message2":"","message3":"","message4":"","minTurns":1,"motion":0,"name":"Retreating","note":"","overlay":0,"priority":50,"removeAtBattleEnd":true,"removeByDamage":false,"removeByRestriction":false,"removeByWalking":false,"restriction":4,"stepsToRemove":100},
{"id":17,"autoRemovalTiming":2,"chanceByDamage":100,"traits":[{"code":22,"dataId":2,"value":0.6},{"code":22,"dataId":1,"value":0.05},{"code":44,"dataId":9,"value":1}],"iconIndex":391,"maxTurns":5,"message1":"","message2":"","message3":"","message4":"","minTurns":5,"motion":0,"name":"In position","note":"","overlay":0,"priority":50,"removeAtBattleEnd":true,"removeByDamage":true,"removeByRestriction":false,"removeByWalking":false,"restriction":0,"stepsToRemove":100},
{"id":18,"autoRemovalTiming":0,"chanceByDamage":100,"traits":[],"iconIndex":0,"maxTurns":1,"message1":"","message2":"","message3":"","message4":"","minTurns":1,"motion":0,"name":"","note":"","overlay":0,"priority":50,"removeAtBattleEnd":false,"removeByDamage":false,"removeByRestriction":false,"removeByWalking":false,"restriction":0,"stepsToRemove":100},
{"id":19,"autoRemovalTiming":0,"chanceByDamage":100,"traits":[],"iconIndex":0,"maxTurns":1,"message1":"","message2":"","message3":"","message4":"","minTurns":1,"motion":0,"name":"","note":"","overlay":0,"priority":50,"removeAtBattleEnd":false,"removeByDamage":false,"removeByRestriction":false,"removeByWalking":false,"restriction":0,"stepsToRemove":100},
{"id":20,"autoRemovalTiming":0,"chanceByDamage":100,"traits":[],"iconIndex":0,"maxTurns":1,"message1":"","message2":"","message3":"","message4":"","minTurns":1,"motion":0,"name":"","note":"","overlay":0,"priority":50,"removeAtBattleEnd":false,"removeByDamage":false,"removeByRestriction":false,"removeByWalking":false,"restriction":0,"stepsToRemove":100},
{"id":21,"autoRemovalTiming":2,"chanceByDamage":100,"traits":[{"code":22,"dataId":1,"value":10}],"iconIndex":633,"maxTurns":2,"message1":"","message2":"","message3":"","message4":"","minTurns":2,"motion":0,"name":"Dodging","note":"<Custom Deselect Effect>\n   user.removeState(21);\n  </Custom Deselect Effect>","overlay":0,"priority":50,"removeAtBattleEnd":true,"removeByDamage":false,"removeByRestriction":false,"removeByWalking":false,"restriction":0,"stepsToRemove":100},
{"id":22,"autoRemovalTiming":0,"chanceByDamage":100,"traits":[],"iconIndex":0,"maxTurns":1,"message1":"","message2":"","message3":"","message4":"","minTurns":1,"motion":0,"name":"Debries","note":"<Ally Aura: 6>  \n<Custom React Effect>\n// Check if this dealt HP damage\nif (this.isHpEffect() && value > 0) {\n$gameTroop.members()[0].startAnimation(1, false, 0);\n  var group = $gameParty.aliveMembers();\n  var rate = 0.055;\n\n  var dmg = Math.floor(value * rate);\n    for (var i = 0; i < group.length; ++i) {\nvar member = group[i];\nif(member.eva>Math.random()){\nif(member.barrierPoints()>=dmg){\nmember.loseBarrier(dmg);\n}else{\ndmg=dmg-member.barrierPoints();\nmember.loseBarrier(Math.floor(member.barrierPoints()));\nmember.gainHp(Math.floor(-dmg/10));\n}\n}\n\nmember.startDamagePopup();\n}}\n</Custom React Effect>","overlay":0,"priority":50,"removeAtBattleEnd":false,"removeByDamage":false,"removeByRestriction":false,"removeByWalking":false,"restriction":4,"stepsToRemove":100},
{"id":23,"autoRemovalTiming":0,"chanceByDamage":100,"traits":[],"iconIndex":0,"maxTurns":1,"message1":"","message2":"","message3":"","message4":"","minTurns":1,"motion":0,"name":"Hurt","note":"<Passive Condition: HP Below 75%>","overlay":0,"priority":50,"removeAtBattleEnd":false,"removeByDamage":false,"removeByRestriction":false,"removeByWalking":false,"restriction":0,"stepsToRemove":100},
{"id":24,"autoRemovalTiming":0,"chanceByDamage":100,"traits":[],"iconIndex":567,"maxTurns":1,"message1":"","message2":"","message3":"","message4":"","minTurns":1,"motion":0,"name":"Damaged","note":"<Passive Condition: HP Below 50%>","overlay":0,"priority":50,"removeAtBattleEnd":false,"removeByDamage":false,"removeByRestriction":false,"removeByWalking":false,"restriction":0,"stepsToRemove":100},
{"id":25,"autoRemovalTiming":0,"chanceByDamage":100,"traits":[{"code":22,"dataId":7,"value":-0.05}],"iconIndex":575,"maxTurns":1,"message1":"","message2":"","message3":"","message4":"","minTurns":1,"motion":0,"name":"Critical","note":"<Passive Condition: HP Below 25%>\n<Custom Turn Start Effect>\nuser.addState(16);\n</Custom Turn Start Effect>","overlay":0,"priority":50,"removeAtBattleEnd":false,"removeByDamage":false,"removeByRestriction":false,"removeByWalking":false,"restriction":0,"stepsToRemove":100},
{"id":26,"autoRemovalTiming":0,"chanceByDamage":100,"traits":[],"iconIndex":0,"maxTurns":1,"message1":"","message2":"","message3":"","message4":"","minTurns":1,"motion":0,"name":"","note":"","overlay":0,"priority":50,"removeAtBattleEnd":false,"removeByDamage":false,"removeByRestriction":false,"removeByWalking":false,"restriction":0,"stepsToRemove":100},
{"id":27,"autoRemovalTiming":0,"chanceByDamage":100,"traits":[],"iconIndex":0,"maxTurns":1,"message1":"","message2":"","message3":"","message4":"","minTurns":1,"motion":0,"name":"","note":"","overlay":0,"priority":50,"removeAtBattleEnd":false,"removeByDamage":false,"removeByRestriction":false,"removeByWalking":false,"restriction":0,"stepsToRemove":100},
{"id":28,"autoRemovalTiming":0,"chanceByDamage":100,"traits":[],"iconIndex":0,"maxTurns":1,"message1":"","message2":"","message3":"","message4":"","minTurns":1,"motion":0,"name":"","note":"","overlay":0,"priority":50,"removeAtBattleEnd":false,"removeByDamage":false,"removeByRestriction":false,"removeByWalking":false,"restriction":0,"stepsToRemove":100},
{"id":29,"autoRemovalTiming":0,"chanceByDamage":100,"traits":[],"iconIndex":0,"maxTurns":1,"message1":"","message2":"","message3":"","message4":"","minTurns":1,"motion":0,"name":"","note":"","overlay":0,"priority":50,"removeAtBattleEnd":false,"removeByDamage":false,"removeByRestriction":false,"removeByWalking":false,"restriction":0,"stepsToRemove":100},
{"id":30,"autoRemovalTiming":0,"chanceByDamage":100,"traits":[],"iconIndex":0,"maxTurns":1,"message1":"","message2":"","message3":"","message4":"","minTurns":1,"motion":0,"name":"","note":"","overlay":0,"priority":50,"removeAtBattleEnd":false,"removeByDamage":false,"removeByRestriction":false,"removeByWalking":false,"restriction":0,"stepsToRemove":100}
]